predicto_video/__init__.py
predicto_video/generator.py
predicto_video/utils.py
predicto-1.1.0.dist-info/LICENSE.txt
predicto-1.1.0.dist-info/METADATA
predicto-1.1.0.dist-info/WHEEL
predicto-1.1.0.dist-info/top_level.txt
predicto-1.1.0.dist-info/RECORD
